umlshapes/ShapeTypes.py
umlshapes/UmlBaseEventHandler.py
umlshapes/UmlDiagram.py
umlshapes/UmlUtils.py
umlshapes/__init__.py
umlshapes/_version.py
umlshapes/py.typed
umlshapes/commands/AbstractBaseCommandMeta.py
umlshapes/commands/ActorCutCommand.py
umlshapes/commands/ActorPasteCommand.py
umlshapes/commands/BaseCommand.py
umlshapes/commands/BaseCutCommand.py
umlshapes/commands/BasePasteCommand.py
umlshapes/commands/ClassCutCommand.py
umlshapes/commands/ClassPasteCommand.py
umlshapes/commands/DeleteLinkCommand.py
umlshapes/commands/NoteCutCommand.py
umlshapes/commands/NotePasteCommand.py
umlshapes/commands/TextCutCommand.py
umlshapes/commands/TextPasteCommand.py
umlshapes/commands/UseCaseCutCommand.py
umlshapes/commands/UseCasePasteCommand.py
umlshapes/commands/__init__.py
umlshapes/commands/py.typed
umlshapes/dialogs/BaseEditDialog.py
umlshapes/dialogs/BaseEditParamFieldDialog.py
umlshapes/dialogs/DlgEditActor.py
umlshapes/dialogs/DlgEditField.py
umlshapes/dialogs/DlgEditInterface.py
umlshapes/dialogs/DlgEditLink.py
umlshapes/dialogs/DlgEditNote.py
umlshapes/dialogs/DlgEditText.py
umlshapes/dialogs/DlgEditUseCase.py
umlshapes/dialogs/__init__.py
umlshapes/dialogs/py.typed
umlshapes/dialogs/preferences/BasePreferencesPanel.py
umlshapes/dialogs/preferences/DefaultValuesPanel.py
umlshapes/dialogs/preferences/DiagramPreferencesPanel.py
umlshapes/dialogs/preferences/NamedSpinCtrl.py
umlshapes/dialogs/preferences/__init__.py
umlshapes/dialogs/preferences/valuepanels/AssociationPreferencesPanel.py
umlshapes/dialogs/preferences/valuepanels/ClassPreferencesPanel.py
umlshapes/dialogs/preferences/valuepanels/DefaultNamesPanel.py
umlshapes/dialogs/preferences/valuepanels/DualSpinners.py
umlshapes/dialogs/preferences/valuepanels/LollipopPreferencesPanel.py
umlshapes/dialogs/preferences/valuepanels/NotePreferencesPanel.py
umlshapes/dialogs/preferences/valuepanels/SDPreferencesPanel.py
umlshapes/dialogs/preferences/valuepanels/TextPreferencesPanel.py
umlshapes-1.5.2.dist-info/licenses/LICENSE
umlshapes-1.5.2.dist-info/METADATA
umlshapes-1.5.2.dist-info/WHEEL
umlshapes-1.5.2.dist-info/top_level.txt
umlshapes-1.5.2.dist-info/RECORD
