Metadata-Version: 2.4
Name: umlshapes
Version: 1.5.2
Summary: Pyut Ogl without homegrown miniogl
Author-email: "Humberto A. Sanchez II" <Humberto.A.Sanchez.II@gmail.com>
Maintainer-email: "Humberto A. Sanchez II" <Humberto.A.Sanchez.II@gmail.com>
License-Expression: AGPL-1.0-or-later
Project-URL: Repository, https://github.com/hasii2011/uml
Keywords: pyut,graphical shapes,python
Classifier: Programming Language :: Python
Classifier: Intended Audience :: Developers
Classifier: Operating System :: MacOS :: MacOS X
Classifier: Topic :: Software Development :: Libraries :: Python Modules
License-File: LICENSE
Requires-Dist: wxPython==4.2.4
Requires-Dist: codeallybasic>=1.30.0
Requires-Dist: codeallyadvanced>=2.2.0
Requires-Dist: umlmodel>=3.4.0
Requires-Dist: human_id==0.2.0
Requires-Dist: Pypubsub==4.0.3
Provides-Extra: test
Requires-Dist: mypy==1.19.0; extra == "test"
Requires-Dist: mypy-extensions==1.1.0; extra == "test"
Requires-Dist: types-Deprecated==1.2.9.20240311; extra == "test"
Requires-Dist: html-testRunner~=1.2.1; extra == "test"
Requires-Dist: pyautogui==0.9.54; extra == "test"
Requires-Dist: pillow==12.0.0; extra == "test"
Provides-Extra: deploy
Requires-Dist: wheel==0.45.1; extra == "deploy"
Requires-Dist: setuptools==80.9.0; extra == "deploy"
Requires-Dist: twine==6.1.0; extra == "deploy"
Requires-Dist: build==1.3.0; extra == "deploy"
Requires-Dist: pkginfo==1.12.1.2; extra == "deploy"
Dynamic: license-file
